{
  "title": "Feasibility Study",
  "slug": "feasibility-study",
  "subject": "Software Engineering",
  "category": "Core Computer Science",
  "level": "Beginner",
  "estimated_read_time": "25 mins",
  "prerequisites": [
    "SDLC"
  ],
  "learning_objectives": [
    "Technical",
    "Operational",
    "Economic"
  ],
  "theory": "Can we build it? Should we? \n1. **Technical**: Do we have tech/skills? \n2. **Economic**: Cost vs Benefit (ROI). \n3. **Operational**: Will used acceptance it?",
  "syntax": "Go/No-Go",
  "examples": [],
  "common_mistakes": [],
  "interview_questions": [],
  "practice_problems": [],
  "real_world_use_cases": [],
  "exam_notes": [],
  "summary": "Reality check."
}