{
  "title": "Software Engineering Tools",
  "slug": "se-tools",
  "subject": "Software Engineering",
  "category": "Core Computer Science",
  "level": "Intermediate",
  "estimated_read_time": "25 mins",
  "prerequisites": [
    "SDLC"
  ],
  "learning_objectives": [
    "CASE",
    "IDE",
    "Version Control",
    "Bug Tracker"
  ],
  "theory": "CASE (Computer Aided Software Engineering). \n- **Management**: Jira. \n- **Design**: StarUML. \n- **Code**: VS Code. \n- **SCM**: Git. \n- **Testing**: Selenium.",
  "syntax": "Toolset",
  "examples": [],
  "common_mistakes": [],
  "interview_questions": [],
  "practice_problems": [],
  "real_world_use_cases": [],
  "exam_notes": [],
  "summary": "Force multipliers."
}