{
  "title": "Real-World DBMS Case Studies",
  "slug": "dbms-case-studies",
  "subject": "Database Management Systems",
  "category": "Core Computer Science",
  "level": "Advanced",
  "estimated_read_time": "30 mins",
  "prerequisites": [
    "All Topics"
  ],
  "learning_objectives": [
    "PostgreSQL vs MySQL",
    "Uber Architecture",
    "Banking Systems"
  ],
  "theory": "- **PostgreSQL**: Advanced, features rich, academic.\n- **MySQL**: Fast, web standard.\n- **Uber**: Moved from Postgres to Schemaless (Mezzanine) due to write throughput.",
  "syntax": "N/A",
  "examples": [],
  "common_mistakes": [],
  "interview_questions": [],
  "practice_problems": [],
  "real_world_use_cases": [],
  "exam_notes": [],
  "summary": "How giants use data."
}