{
  "title": "Query Optimization",
  "slug": "query-optimization",
  "subject": "Database Management Systems",
  "category": "Core Computer Science",
  "level": "Advanced",
  "estimated_read_time": "30 mins",
  "prerequisites": [
    "Query Processing"
  ],
  "learning_objectives": [
    "Cost Estimation",
    "Heuristic Optimization",
    "Filter Pushdown"
  ],
  "theory": "Improving query speed. \n**Heuristics**: \n- Perform Selection (Filtering) as early as possible (reduce rows before Join).\n- Use Indexes.\n**Cost Based**: Estimate disk I/O for different join orders.",
  "syntax": "N/A",
  "examples": [
    {
      "code": "SELECT * FROM A, B WHERE A.id=B.id AND A.val=5.\nBad: Join A & B (huge), then filter.\nGood: Filter A (small), then Join.",
      "output": "Performance",
      "explanation": "Reduce intermediate results."
    }
  ],
  "common_mistakes": [],
  "interview_questions": [],
  "practice_problems": [],
  "real_world_use_cases": [],
  "exam_notes": [
    "Selectivity factor."
  ],
  "summary": "Working smarter, not harder."
}