{
  "title": "HAVING Clause",
  "slug": "sql-having",
  "subject": "Database Management Systems",
  "category": "Core Computer Science",
  "level": "Intermediate",
  "estimated_read_time": "20 mins",
  "prerequisites": [
    "GROUP BY Clause"
  ],
  "learning_objectives": [
    "Filtering Groups",
    "HAVING vs WHERE"
  ],
  "theory": "Filters the RESULT of aggregation. \n- `WHERE`: Filters rows BEFORE grouping.\n- `HAVING`: Filters groups AFTER aggregation.",
  "syntax": "GROUP BY Dept HAVING SUM(Salary) > 1000",
  "examples": [],
  "common_mistakes": [
    {
      "mistake": "Using WHERE for Aggregates",
      "correction": "WHERE SUM(Salary) > 1000 is IDIOTIC. The sum doesn't exist yet. Use HAVING.",
      "example": "Syntax Error."
    }
  ],
  "interview_questions": [
    {
      "question": "Can we use HAVING without GROUP BY?",
      "answer": "Yes, it treats the whole table as one group (like an aggregate check). Rare usage.",
      "difficulty": "Advanced"
    }
  ],
  "practice_problems": [],
  "real_world_use_cases": [],
  "exam_notes": [
    "Order: FROM -> WHERE -> GROUP BY -> HAVING -> SELECT."
  ],
  "summary": "Filtering the summary.",
  "order": 28
}