{
  "title": "Heap Data Structure",
  "slug": "heap-ds",
  "subject": "Data Structures",
  "category": "Core Computer Science",
  "level": "Intermediate",
  "estimated_read_time": "30 mins",
  "prerequisites": [
    "Binary Tree"
  ],
  "learning_objectives": [
    "Max Heap vs Min Heap",
    "Complete Binary Tree representation in Array",
    "Heapify"
  ],
  "theory": "A complete binary tree where parent is always >= children (Max Heap). Implemented using Arrays.\n- Parent(i) -> `(i-1)/2`\n- Left(i) -> `2*i + 1`\n- Right(i) -> `2*i + 2`.",
  "syntax": "Array: [100, 19, 36, 17, 3, 25]",
  "examples": [],
  "common_mistakes": [],
  "interview_questions": [
    {
      "question": "Difference between Heap and BST?",
      "answer": "Heap guarantees Parent > Children (Order). BST guarantees Left < Parent < Right (Sorting). Heap search is O(n), BST is O(log n).",
      "difficulty": "Medium"
    }
  ],
  "practice_problems": [],
  "real_world_use_cases": [],
  "exam_notes": [
    "Root is Max/Min.",
    "Array indices start at 0."
  ],
  "summary": "Efficient implementation of Priority Queues."
}