{
  "title": "C Best Practices",
  "slug": "c-best-practices",
  "subject": "C Programming",
  "category": "Programming Language",
  "level": "Advanced",
  "estimated_read_time": "25 mins",
  "prerequisites": [
    "All Topics"
  ],
  "learning_objectives": [
    "Naming Conventions",
    "Comments",
    "Safety",
    "const correctness"
  ],
  "theory": "Writing maintainable C. \n- Use `const` pointers where possible.\n- Check malloc return values.\n- Avoid global variables.\n- Use `snprintf` instead of `sprintf` (Buffer overflow).",
  "syntax": "Clean Code",
  "examples": [],
  "common_mistakes": [],
  "interview_questions": [],
  "practice_problems": [],
  "real_world_use_cases": [],
  "exam_notes": [],
  "summary": "Professional grade.",
  "order": 3
}