{
  "title": "System Calls",
  "slug": "system-calls",
  "subject": "Operating Systems",
  "category": "Core Computer Science",
  "level": "Beginner",
  "estimated_read_time": "25 mins",
  "prerequisites": [
    "User Mode vs Kernel Mode"
  ],
  "learning_objectives": [
    "API",
    "Types of Calls",
    "strace"
  ],
  "theory": "The interface between a process and the OS. When an app needs file access, network, or new process, it invokes a System Call (e.g., `open()`, `fork()`, `read()`).\nIt triggers a software interrupt (Trap).",
  "syntax": "fd = open(\"file.txt\", O_RDONLY);",
  "examples": [
    {
      "code": "printf(\"Hello\");\n// Calls write() system call internally.",
      "output": "Hello",
      "explanation": "Standard libraries wrap raw system calls."
    }
  ],
  "common_mistakes": [],
  "interview_questions": [
    {
      "question": "Difference between API and System Call?",
      "answer": "API (like Win32 API or POSIX) is a user-level definition. System call is the actual kernel entry point.",
      "difficulty": "Medium"
    }
  ],
  "practice_problems": [],
  "real_world_use_cases": [],
  "exam_notes": [
    "fork(), exec(), exit(), wait()."
  ],
  "summary": "The phone call a program makes to the Kernel.",
  "order": 46
}