{
  "title": "Floating Point Representation",
  "slug": "floating-point",
  "subject": "Computer Organization",
  "category": "Core Computer Science",
  "level": "Beginner",
  "estimated_read_time": "35 mins",
  "prerequisites": [
    "Signed Number Representation"
  ],
  "learning_objectives": [
    "IEEE 754",
    "Sign",
    "Exponent",
    "Mantissa"
  ],
  "theory": "Representing real numbers (decimals). \nScientific notation in binary: `(-1)^S * 1.M * 2^(E-Bias)`. \n- **Single Precision (32-bit)**: 1 Sign, 8 Exp, 23 Mantissa. \n- **Double (64-bit)**: 1 Sign, 11 Exp, 52 Mantissa.",
  "syntax": "float",
  "examples": [],
  "common_mistakes": [
    {
      "mistake": "Precision loss",
      "correction": "0.1 + 0.2 != 0.3 in float. Due to binary repeating fraction.",
      "example": "Accuracy."
    }
  ],
  "interview_questions": [
    {
      "question": "What is Bias?",
      "answer": "Offset added to exponent to handle negative exponents without sign bit (e.g., 127 for float).",
      "difficulty": "Medium"
    }
  ],
  "practice_problems": [],
  "real_world_use_cases": [],
  "exam_notes": [],
  "summary": "Real numbers."
}