{
  "title": "Bootstrap Interview Preparation",
  "slug": "bootstrap-interview",
  "subject": "Bootstrap",
  "category": "Frontend Framework",
  "level": "Advanced",
  "estimated_read_time": "20 mins",
  "prerequisites": [
    "All Topics"
  ],
  "learning_objectives": [
    "Grid mechanics",
    "Utility classes",
    "JS integration",
    "Comparisons"
  ],
  "theory": "## Test Yourself\n\n### Common Questions\n1. **Reset vs Normalize vs Reboot**: Bootstrap uses Reboot (built on Normalize) to standardize defaults.\n2. **Container vs Container-Fluid**.\n3. **Explain the Grid System math**.\n4. **Bootstrap vs Tailwind**: Bootstrap = Components (Faster start). Tailwind = Utilities (More flexibility).\n5. **Semantic Class Names**: Why strictly using `col-md-6` might be considered non-semantic.",
  "syntax": "N/A",
  "examples": [],
  "common_mistakes": [],
  "interview_questions": [],
  "practice_problems": [],
  "real_world_use_cases": [],
  "exam_notes": [],
  "summary": "A review of the technical depth behind the framework.",
  "order": 20
}